MANIFEST.in
README.rst
VERSION
conftest.py
requirements.txt
setup.cfg
setup.py
PyPiwi.egg-info/PKG-INFO
PyPiwi.egg-info/SOURCES.txt
PyPiwi.egg-info/dependency_links.txt
PyPiwi.egg-info/requires.txt
PyPiwi.egg-info/top_level.txt
docs/Makefile
docs/conf.py
docs/index.rst
pypiwi/__init__.py
tests/test_default.py
tests/test_distill.py
tests/test_package.py