Metadata-Version: 1.1
Name: PyPiwi
Version: 1.4
Summary: Piwi; Peewee, more.
Home-page: https://bitbucket.org/creeerio/pypiwi
Author: Nils
Author-email: nils@creeer.io
License: MIT
Platform: UNKNOWN
Classifier: Development Status :: 3 - Alpha
Classifier: Intended Audience :: Developers
Classifier: License :: OSI Approved :: MIT License
Classifier: Programming Language :: Python :: 3.5
